pylibfinder.cpython-314-x86_64-linux-gnu.so
pylibfinder-0.2.1.dist-info/METADATA
pylibfinder-0.2.1.dist-info/WHEEL
pylibfinder-0.2.1.dist-info/top_level.txt
pylibfinder-0.2.1.dist-info/RECORD
pylibfinder-0.2.1.dist-info/licenses/LICENSE
