Metadata-Version: 2.4
Name: pylibfinder
Version: 0.2.1
Summary: Library to spot a keyword as a function inside python stdlib
Author-email: Prince Roshan <princekrroshan01@gmail.com>
License: MIT
Keywords: C-extension
Classifier: Programming Language :: Python :: 3.10
Classifier: Programming Language :: Python :: 3.11
Classifier: Programming Language :: Python :: 3.12
Classifier: Programming Language :: Python :: 3.13
Classifier: Programming Language :: Python :: 3.14
Classifier: Operating System :: MacOS :: MacOS X
Classifier: Operating System :: POSIX
Classifier: License :: OSI Approved :: MIT License
Requires-Python: >=3.10
License-File: LICENSE
Dynamic: license-file
